SVRGoptimizerKeras/__init__.py
SVRGoptimizerKeras/optimizer.py
svrg_optimizer_keras-0.1.0.dist-info/METADATA
svrg_optimizer_keras-0.1.0.dist-info/RECORD
svrg_optimizer_keras-0.1.0.dist-info/WHEEL
svrg_optimizer_keras-0.1.0.dist-info/top_level.txt
