Metadata-Version: 2.1
Name: svrg-optimizer-keras
Version: 0.1.0
Summary: SVGR optimizer for Keras
Home-page: https://github.com/tilkb/SVRGoptimizerKeras
Author: Bence Tilk
Author-email: bence.tilk@gmail.com
License: UNKNOWN
Keywords: SVRG,Keras,Optimizer
Platform: UNKNOWN
Classifier: Programming Language :: Python :: 3
Classifier: License :: OSI Approved :: MIT License
Classifier: Operating System :: OS Independent
Requires-Dist: keras (>=2.2)
